substreams/__init__.py
substreams/substream.py
substreams-0.0.8.dist-info/LICENSE.txt
substreams-0.0.8.dist-info/METADATA
substreams-0.0.8.dist-info/WHEEL
substreams-0.0.8.dist-info/top_level.txt
substreams-0.0.8.dist-info/RECORD
