Metadata-Version: 2.1
Name: substreams
Version: 0.0.8
Summary: WIP Substreams Python Adapter
Home-page: https://github.com/messari/substreams-python
Author: Ryan Sudhakaran
Author-email: Ryan Sudhakaran <ryan.sudhakaran@messari.io>, Michael Carroll <michaelcarroll1999@gmail.com>
Classifier: Programming Language :: Python :: 3
Classifier: License :: OSI Approved :: MIT License
Classifier: Operating System :: OS Independent
Requires-Python: >=3.9
License-File: LICENSE.txt
Requires-Dist: pandas (==1.5.1)
Requires-Dist: protobuf (==3.20.1)
Requires-Dist: grpcio (==1.50.0)
Requires-Dist: grpcio-tools (==1.48.2)
Requires-Dist: ipykernel (==6.17.0)
